setup.py
testpip/__init__.py
testpip/test_install.py
testpip_install.egg-info/PKG-INFO
testpip_install.egg-info/SOURCES.txt
testpip_install.egg-info/dependency_links.txt
testpip_install.egg-info/not-zip-safe
testpip_install.egg-info/top_level.txt