Metadata-Version: 1.0
Name: testpip-install
Version: 0.1
Summary: test pip install how to use
Home-page: http://github.com/tongling/clinicaltrial
Author: Ling
Author-email: aguan.zhang@megatronix.co
License: MIT
Platform: UNKNOWN
